Logger/__init__.py
Logger/log.py
axixalogger-0.0.0.dist-info/METADATA
axixalogger-0.0.0.dist-info/WHEEL
axixalogger-0.0.0.dist-info/top_level.txt
axixalogger-0.0.0.dist-info/RECORD
