Metadata-Version: 2.4
Name: axixalogger
Version: 0.0.0
Summary: Simple logger just for demo purpose
Author: Sunil Tiwari
Author-email: hello@suniltiwari.dev
Classifier: Programming Language :: Python :: 3
Dynamic: author
Dynamic: author-email
Dynamic: classifier
Dynamic: summary
